moxel_python_driver/__init__.py
moxel_python_driver/driver.py
moxel_python_driver-0.0.1.post57.dist-info/DESCRIPTION.rst
moxel_python_driver-0.0.1.post57.dist-info/METADATA
moxel_python_driver-0.0.1.post57.dist-info/RECORD
moxel_python_driver-0.0.1.post57.dist-info/WHEEL
moxel_python_driver-0.0.1.post57.dist-info/entry_points.txt
moxel_python_driver-0.0.1.post57.dist-info/metadata.json
moxel_python_driver-0.0.1.post57.dist-info/top_level.txt
