Metadata-Version: 2.0
Name: moxel-python-driver
Version: 0.0.1.post57
Summary: python driver for moxel models
Home-page: UNKNOWN
Author: moxel
Author-email: support@moxel.ai
License: MIT
Platform: UNKNOWN
